randomjoke/__init__.py
randomjoke/cli.py
randomjoke/randomjoke.py
randomjoke-1.0.0.dist-info/AUTHORS.rst
randomjoke-1.0.0.dist-info/LICENSE
randomjoke-1.0.0.dist-info/METADATA
randomjoke-1.0.0.dist-info/WHEEL
randomjoke-1.0.0.dist-info/entry_points.txt
randomjoke-1.0.0.dist-info/top_level.txt
randomjoke-1.0.0.dist-info/RECORD
