Metadata-Version: 2.1
Name: randomjoke
Version: 1.0.0
Summary: Display a random joke from https://icanhazdadjoke.com API
Home-page: https://github.com/codehutlabs/randomjoke
Author: Robert Kuzma
Author-email: robert@codehut.io
License: MIT license
Keywords: randomjoke
Platform: UNKNOWN
Classifier: Development Status :: 2 - Pre-Alpha
Classifier: Intended Audience :: Developers
Classifier: License :: OSI Approved :: MIT License
Classifier: Natural Language :: English
Classifier: Programming Language :: Python :: 3
Classifier: Programming Language :: Python :: 3.5
Classifier: Programming Language :: Python :: 3.6
Classifier: Programming Language :: Python :: 3.7
Classifier: Programming Language :: Python :: 3.8
Requires-Python: !=2.7, !=3.0.*, !=3.1.*, !=3.2.*, !=3.3.*, !=3.4.*
Requires-Dist: Click (>=7.0)
Requires-Dist: requests (>=2.22.0)
